lavaru_capital/__init__.py
lavaru_capital/varu_data.py
lavaru_capital-0.1.2.dist-info/LICENSE
lavaru_capital-0.1.2.dist-info/METADATA
lavaru_capital-0.1.2.dist-info/WHEEL
lavaru_capital-0.1.2.dist-info/top_level.txt
lavaru_capital-0.1.2.dist-info/RECORD
